jupyter_markdown/__init__.py
jupyter_markdown/_version.py
jupyter_markdown/handlers.py
jupyter_markdown/tests/__init__.py
jupyter_markdown/tests/test_handlers.py
jupyter_markdown-0.0.2.data/data/etc/jupyter/jupyter_notebook_config.d/jupyter_markdown.json
jupyter_markdown-0.0.2.data/data/etc/jupyter/jupyter_server_config.d/jupyter_markdown.json
jupyter_markdown-0.0.2.data/data/share/jupyter/labextensions/@datalayer/jupyter-markdown/build_log.json
jupyter_markdown-0.0.2.data/data/share/jupyter/labextensions/@datalayer/jupyter-markdown/package.json
jupyter_markdown-0.0.2.data/data/share/jupyter/labextensions/@datalayer/jupyter-markdown/schemas/@datalayer/jupyter-admin/package.json.orig
jupyter_markdown-0.0.2.data/data/share/jupyter/labextensions/@datalayer/jupyter-markdown/schemas/@datalayer/jupyter-admin/plugin.json
jupyter_markdown-0.0.2.data/data/share/jupyter/labextensions/@datalayer/jupyter-markdown/static/lib_index_js.4348b810ae8dc12e002f.js
jupyter_markdown-0.0.2.data/data/share/jupyter/labextensions/@datalayer/jupyter-markdown/static/lib_index_js.4348b810ae8dc12e002f.js.map
jupyter_markdown-0.0.2.data/data/share/jupyter/labextensions/@datalayer/jupyter-markdown/static/remoteEntry.60045aa25abfdbe55e4f.js
jupyter_markdown-0.0.2.data/data/share/jupyter/labextensions/@datalayer/jupyter-markdown/static/remoteEntry.60045aa25abfdbe55e4f.js.map
jupyter_markdown-0.0.2.data/data/share/jupyter/labextensions/@datalayer/jupyter-markdown/static/style.js
jupyter_markdown-0.0.2.data/data/share/jupyter/labextensions/@datalayer/jupyter-markdown/static/style_index_js.09ea6e1de3ce833faf40.js
jupyter_markdown-0.0.2.data/data/share/jupyter/labextensions/@datalayer/jupyter-markdown/static/style_index_js.09ea6e1de3ce833faf40.js.map
jupyter_markdown-0.0.2.data/data/share/jupyter/labextensions/@datalayer/jupyter-markdown/static/vendors-node_modules_css-loader_dist_runtime_api_js-node_modules_css-loader_dist_runtime_cssW-72eba1.bac0ab4f283009af8f3d.js
jupyter_markdown-0.0.2.dist-info/METADATA
jupyter_markdown-0.0.2.dist-info/WHEEL
jupyter_markdown-0.0.2.dist-info/licenses/LICENSE
jupyter_markdown-0.0.2.dist-info/RECORD
